{"angle": [0, 0, 0, 0], "number_of_connected_edges": 1, "id": 38, "children": [{"angle": [0.12098765432098765, 0, 0, 0], "number_of_connected_edges": 2, "id": 11, "children": [{"angle": [0.0014814814814814812, 0, 0, 0], "number_of_connected_edges": 2, "id": 52, "children": [{"angle": [0, 0, 0, 0], "number_of_connected_edges": 0, "id": 20}, {"angle": [0, 0, 0, 0], "number_of_connected_edges": 0, "id": 54}]}, {"angle": [-0.1322222222222222, 0, 0, 0], "number_of_connected_edges": 2, "id": 5, "children": [{"angle": [0, 0, 0, 0], "number_of_connected_edges": 1, "id": 27, "children": [{"angle": [0, 0, 0, 0], "number_of_connected_edges": 0, "id": 49}]}, {"angle": [-0.009135802469135802, 0, 0, 0], "number_of_connected_edges": 2, "id": 32, "children": [{"angle": [0, 0, 0, 0], "number_of_connected_edges": 0, "id": 65}, {"angle": [-0.043333333333333335, 0, 0, 0], "number_of_connected_edges": 2, "id": 12, "children": [{"angle": [0, 0, 0, 0], "number_of_connected_edges": 0, "id": 10}, {"angle": [-0.16530864197530865, 0.1580246913580247, 0, 0], "number_of_connected_edges": 3, "id": 90, "children": [{"angle": [0, 0, 0, 0], "number_of_connected_edges": 0, "id": 50}, {"angle": [0, 0, 0, 0], "number_of_connected_edges": 1, "id": 51, "children": [{"angle": [0, 0, 0, 0], "number_of_connected_edges": 0, "id": 73}]}, {"angle": [0, 0, 0, 0], "number_of_connected_edges": 1, "id": 92, "children": [{"angle": [0, 0, 0, 0], "number_of_connected_edges": 0, "id": 91}]}]}]}]}]}]}]}