{"angle": [-0.03209876543209877, 0, 0, 0], "number_of_connected_edges": 2, "id": 26, "children": [{"angle": [0, 0, 0, 0], "number_of_connected_edges": 0, "id": 31}, {"angle": [0, 0, 0, 0], "number_of_connected_edges": 1, "id": 32, "children": [{"angle": [0, 0, 0, 0], "number_of_connected_edges": 1, "id": 64, "children": [{"angle": [0.055308641975308645, 0.013827160493827161, 0, 0], "number_of_connected_edges": 3, "id": 25, "children": [{"angle": [0, 0, 0, 0], "number_of_connected_edges": 0, "id": 59}, {"angle": [0, 0, 0, 0], "number_of_connected_edges": 1, "id": 19, "children": [{"angle": [0.10493827160493828, 0, 0, 0], "number_of_connected_edges": 2, "id": 17, "children": [{"angle": [0, 0, 0, 0], "number_of_connected_edges": 0, "id": 40}, {"angle": [0, 0, 0, 0], "number_of_connected_edges": 1, "id": 60, "children": [{"angle": [0, 0, 0, 0], "number_of_connected_edges": 0, "id": 75}]}]}]}, {"angle": [0, 0, 0, 0], "number_of_connected_edges": 1, "id": 23, "children": [{"angle": [0, 0, 0, 0], "number_of_connected_edges": 1, "id": 65, "children": [{"angle": [-0.03666666666666667, 0, 0, 0], "number_of_connected_edges": 2, "id": 44, "children": [{"angle": [0, 0, 0, 0], "number_of_connected_edges": 0, "id": 14}, {"angle": [0, 0, 0, 0], "number_of_connected_edges": 1, "id": 79, "children": [{"angle": [0, 0, 0, 0], "number_of_connected_edges": 0, "id": 30}]}]}]}]}]}]}]}]}