{"angle": [0, 0, 0, 0], "number_of_connected_edges": 1, "id": 58, "children": [{"angle": [0, 0, 0, 0], "number_of_connected_edges": 1, "id": 33, "children": [{"angle": [0, 0, 0, 0], "number_of_connected_edges": 1, "id": 78, "children": [{"angle": [-0.06938271604938272, -0.011604938271604937, 0, 0], "number_of_connected_edges": 3, "id": 30, "children": [{"angle": [0, 0, 0, 0], "number_of_connected_edges": 1, "id": 40, "children": [{"angle": [0, 0, 0, 0], "number_of_connected_edges": 0, "id": 48}]}, {"angle": [0, 0, 0, 0], "number_of_connected_edges": 0, "id": 59}, {"angle": [0.14012345679012345, 0, 0, 0], "number_of_connected_edges": 2, "id": 89, "children": [{"angle": [0, 0, 0, 0], "number_of_connected_edges": 1, "id": 55, "children": [{"angle": [0, 0, 0, 0], "number_of_connected_edges": 0, "id": 39}]}, {"angle": [0, 0, 0, 0], "number_of_connected_edges": 1, "id": 67, "children": [{"angle": [0, 0, 0, 0], "number_of_connected_edges": 1, "id": 81, "children": [{"angle": [0.05506172839506173, 0, 0, 0], "number_of_connected_edges": 2, "id": 43, "children": [{"angle": [0, 0, 0, 0], "number_of_connected_edges": 0, "id": 10}, {"angle": [0, 0, 0, 0], "number_of_connected_edges": 0, "id": 24}]}]}]}]}]}]}]}]}