{"angle": [0, 0, 0, 0], "number_of_connected_edges": 1, "id": 21, "children": [{"angle": [0, 0, 0, 0], "number_of_connected_edges": 1, "id": 44, "children": [{"angle": [0, 0, 0, 0], "number_of_connected_edges": 1, "id": 88, "children": [{"angle": [-0.07888888888888888, -0.02703703703703704, 0, 0], "number_of_connected_edges": 3, "id": 65, "children": [{"angle": [0, 0, 0, 0], "number_of_connected_edges": 0, "id": 3}, {"angle": [0, 0, 0, 0], "number_of_connected_edges": 1, "id": 6, "children": [{"angle": [0, 0, 0, 0], "number_of_connected_edges": 1, "id": 26, "children": [{"angle": [0, 0, 0, 0], "number_of_connected_edges": 0, "id": 8}]}]}, {"angle": [0, 0, 0, 0], "number_of_connected_edges": 1, "id": 45, "children": [{"angle": [0, 0, 0, 0], "number_of_connected_edges": 0, "id": 92}]}]}]}]}]}