{"angle": [-0.0565432098765432, -0.1130864197530864, 0, 0], "number_of_connected_edges": 3, "id": 19, "children": [{"angle": [0, 0, 0, 0], "number_of_connected_edges": 1, "id": 14, "children": [{"angle": [0, 0, 0, 0], "number_of_connected_edges": 1, "id": 57, "children": [{"angle": [0, 0, 0, 0], "number_of_connected_edges": 0, "id": 15}]}]}, {"angle": [0, 0, 0, 0], "number_of_connected_edges": 1, "id": 49, "children": [{"angle": [0, 0, 0, 0], "number_of_connected_edges": 1, "id": 92, "children": [{"angle": [0, 0, 0, 0], "number_of_connected_edges": 1, "id": 93, "children": [{"angle": [0, 0, 0, 0], "number_of_connected_edges": 0, "id": 28}]}]}]}, {"angle": [0.12049382716049384, 0.01345679012345679, 0, 0], "number_of_connected_edges": 3, "id": 60, "children": [{"angle": [0, 0, 0, 0], "number_of_connected_edges": 0, "id": 41}, {"angle": [0, 0, 0, 0], "number_of_connected_edges": 1, "id": 21, "children": [{"angle": [0, 0, 0, 0], "number_of_connected_edges": 0, "id": 56}]}, {"angle": [-0.016049382716049384, 0, 0, 0], "number_of_connected_edges": 2, "id": 40, "children": [{"angle": [0, 0, 0, 0], "number_of_connected_edges": 0, "id": 63}, {"angle": [-0.16703703703703704, 0, 0, 0], "number_of_connected_edges": 2, "id": 94, "children": [{"angle": [0, 0, 0, 0], "number_of_connected_edges": 0, "id": 73}, {"angle": [0, 0, 0, 0], "number_of_connected_edges": 0, "id": 79}]}]}]}]}